{"type":"header","name":"Header group","sections":{"announcement-bar":{"type":"announcement-bar","blocks":{"message_dzVHKH":{"type":"message","settings":{"text":"<strong>End of Spring Sale - Up to 60% OFF<\/strong>"}},"message_XbTQRU":{"type":"message","settings":{"text":"Free Shipping Over USD $110"}},"message_qXi9Py":{"type":"message","settings":{"text":"★★★★★ 70,000+ 5-Star Reviews"}},"message-1":{"type":"message","settings":{"text":"Lifetime Warranty | Easy Returns"}},"message_9DTYzJ":{"type":"message","disabled":true,"settings":{"text":"Ethical Production | Conflict Free"}}},"block_order":["message_dzVHKH","message_XbTQRU","message_qXi9Py","message-1","message_9DTYzJ"],"custom_css":[".announcement-bar {padding: 5px;}","p.prose.heading {font-family: Century Gothic; font-size: 16px; font-weight: 500; letter-spacing: text-align: center;}"],"settings":{"color_scheme":"scheme-3","enable_sticky":true,"autoplay":true,"cycle_speed":5,"desktop_font_size":12,"mobile_font_size":12}},"header":{"type":"header","custom_css":[".h6 {font-family: \"century gothic\"; font-size: 0.95em;}"],"settings":{"color_scheme":"","enable_sticky":false,"hide_on_scroll":false,"show_separation_border":true,"reduce_padding":false,"logo":"shopify:\/\/shop_images\/LOGO_NEW_11d39dc0-aff7-48fa-b1cd-8b66834f766b.png","logo_max_width":200,"logo_mobile_max_width":150,"menu":"menu-lan-v1","sidebar_menu":"menu-lan-v1","menu_open_trigger":"hover","enable_search":true,"sidebar_color_scheme":"","sidebar_text_font":"body","sidebar_show_dividers":true,"layout":"logo_left_navigation_center","show_icons":true,"show_country_selector":true,"show_country_name":false,"show_country_flag":true,"show_locale_selector":false,"transparent_header_text_color":"#ffffff"}}},"order":["announcement-bar","header"]}